.gitignore
CHANGES.txt
CONTRIBUTORS.txt
Gemfile
Gemfile.lock
MANIFEST.in
README.txt
bootstrap.py
setup.py
docs/HISTORY.txt
docs/LICENSE.GPL
docs/LICENSE.txt
src/slc/__init__.py
src/slc.docconv.egg-info/PKG-INFO
src/slc.docconv.egg-info/SOURCES.txt
src/slc.docconv.egg-info/dependency_links.txt
src/slc.docconv.egg-info/entry_points.txt
src/slc.docconv.egg-info/namespace_packages.txt
src/slc.docconv.egg-info/not-zip-safe
src/slc.docconv.egg-info/requires.txt
src/slc.docconv.egg-info/top_level.txt
src/slc/docconv/__init__.py
src/slc/docconv/convert.py
src/slc/docconv/permissions.py
src/slc/docconv/setuphandlers.py
src/slc/docconv/testing.py
src/slc/docconv/tests/__init__.py
src/slc/docconv/tests/test_convert.py