Metadata-Version: 1.1
Name: slc.docconv
Version: 1.3
Summary: Add-on for collective.documentviewer that allows web service like conversion
Home-page: http://syslab.com/
Author: Syslab.com GmbH
Author-email: info@syslab.com
License: gpl
Keywords: collective documentviewer conversion pdf office
Platform: UNKNOWN
Classifier: Programming Language :: Python
